labelprint/__init__.py
labelprint/label.js
labelprint/label.py
labelprint/web.py
labelprint-1.0.5.dist-info/licenses/LICENSE
labelprint-1.0.5.dist-info/METADATA
labelprint-1.0.5.dist-info/WHEEL
labelprint-1.0.5.dist-info/top_level.txt
labelprint-1.0.5.dist-info/RECORD
