Metadata-Version: 2.4
Name: labelprint
Version: 1.0.5
Summary: Automated barcode label generation and printing in Python
Author-email: Pecacheu <3608878+Pecacheu@users.noreply.github.com>
Project-URL: Homepage, https://github.com/Pecacheu/LabelPrint
Project-URL: Issues, https://github.com/Pecacheu/LabelPrint/issues
Classifier: Programming Language :: Python :: 3
Classifier: License :: OSI Approved :: MIT License
Classifier: Operating System :: Microsoft :: Windows
Requires-Python: >=3.10
License-File: LICENSE
Dynamic: license-file
